is_likelion/__init__.py
is_likelion/is_likelion.py
tests/__init__.py
tests/test_is_likelion.py
is_likelion-0.0.4.dist-info/METADATA
is_likelion-0.0.4.dist-info/WHEEL
is_likelion-0.0.4.dist-info/top_level.txt
is_likelion-0.0.4.dist-info/RECORD
