Metadata-Version: 2.1
Name: is-likelion
Version: 0.0.4
Summary: UNKNOWN
Home-page: https://github.com/shinkeonkim/is_likelion
Author: shinkeonkim
Author-email: singun11@gmail.com
License: MIT
Keywords: likelion
Platform: UNKNOWN
Requires-Python: >=3
